setup.py
distributions_learning/Binomialdistribution.py
distributions_learning/Gaussiandistribution.py
distributions_learning/Generaldistribution.py
distributions_learning/__init__.py
distributions_learning.egg-info/PKG-INFO
distributions_learning.egg-info/SOURCES.txt
distributions_learning.egg-info/dependency_links.txt
distributions_learning.egg-info/not-zip-safe
distributions_learning.egg-info/top_level.txt