Metadata-Version: 1.0
Name: distributions-learning
Version: 0.1
Summary: Learning of Gaussian and binomial distributions
Home-page: UNKNOWN
Author: UNKNOWN
Author-email: sudipta.mal87@gmail.com
License: UNKNOWN
Platform: UNKNOWN
